paysafecard/__init__.py
paysafecard/example.py
paysafecard/main.py
paysafecard-0.2.4.dist-info/DESCRIPTION.rst
paysafecard-0.2.4.dist-info/METADATA
paysafecard-0.2.4.dist-info/metadata.json
paysafecard-0.2.4.dist-info/RECORD
paysafecard-0.2.4.dist-info/top_level.txt
paysafecard-0.2.4.dist-info/WHEEL
