Metadata-Version: 2.0
Name: paysafecard
Version: 0.2.4
Summary: A paysafecard class to help with classic payment api.
Home-page: https://github.com/opencbsoft/paysafecard-python
Author: Cristian Boboc
Author-email: cristi@pidginhost.com
License: MIT
Keywords: paysafecard payment class
Platform: UNKNOWN
Classifier: Development Status :: 4 - Beta
Classifier: Intended Audience :: Developers
Classifier: Topic :: Software Development :: Libraries :: Python Modules
Classifier: License :: OSI Approved :: MIT License
Classifier: Programming Language :: Python :: 3
Classifier: Programming Language :: Python :: 3.2
Classifier: Programming Language :: Python :: 3.3
Classifier: Programming Language :: Python :: 3.4
Requires-Dist: suds-jurko
